ace_metrics/__init__.py
ace_metrics/cli.py
ace_metrics/config.py
ace_metrics/helpers.py
ace_metrics/alerts/__init__.py
ace_metrics/alerts/alert_types.py
ace_metrics/alerts/constants.py
ace_metrics/alerts/functions.py
ace_metrics/alerts/users.py
ace_metrics/events/__init__.py
ace_metrics/events/constants.py
ace_metrics/events/functions.py
ace_metrics/plotly_dash/__init__.py
ace_metrics/plotly_dash/app.py
ace_metrics/plotly_dash/database.py
ace_metrics/plotly_dash/helpers.py
ace_metrics/plotly_dash/assets/custom.css
ace_metrics/plotly_dash/assets/custom.js
ace_metrics/plotly_dash/data_exceptions/__init__.py
ace_metrics/plotly_dash/data_exceptions/erik_sep_pv_mishap.py
ace_metrics/plotly_dash/pages/__init__.py
ace_metrics/plotly_dash/pages/alerts.py
ace_metrics/plotly_dash/pages/hours_of_operation.py
ace_metrics/plotly_dash/pages/settings.py
ace_metrics-0.2.3.data/scripts/ace-metrics
ace_metrics-0.2.3.dist-info/LICENSE
ace_metrics-0.2.3.dist-info/METADATA
ace_metrics-0.2.3.dist-info/WHEEL
ace_metrics-0.2.3.dist-info/top_level.txt
ace_metrics-0.2.3.dist-info/RECORD
