Metadata-Version: 2.1
Name: ace-metrics
Version: 0.2.3
Summary: A lib for measuring ACE based IDR operations.
Home-page: https://github.com/seanmcfeely/ace-metrics
Author: Sean McFeely
Author-email: mcfeelynaes@gmail.com
License: GNU General Public License v3.0
Keywords: Information Security,ACE,ACE Ecosystem
Platform: UNKNOWN
Classifier: Development Status :: 3 - Alpha
Classifier: Intended Audience :: Developers
Classifier: Intended Audience :: Information Technology
Classifier: License :: OSI Approved :: GNU General Public License v3 (GPLv3)
Classifier: Programming Language :: Python :: 3 :: Only
Classifier: Programming Language :: Python :: 3
Requires-Python: >=3.6
Requires-Dist: argcomplete
Requires-Dist: businesstime
Requires-Dist: coloredlogs
Requires-Dist: configparser
Requires-Dist: dash-bootstrap-components
Requires-Dist: dash-bootstrap-templates
Requires-Dist: openpyxl
Requires-Dist: pandas <2.0.0
Requires-Dist: pandas-bokeh
Requires-Dist: pymysql
Requires-Dist: sqlite-utils
Requires-Dist: tabulate
